catsoop_grade_calculator/__init__.py
catsoop_grade_calculator/general.py
catsoop_grade_calculator/parsers/__init__.py
catsoop_grade_calculator/parsers/base_parser.py
catsoop_grade_calculator/parsers/circuits.py
catsoop_grade_calculator/parsers/py.py
catsoop_grade_calculator/parsers/request.py
catsoop_grade_calculator/token.txt
catsoop_grade_calculator-0.1.5.dist-info/LICENSE
catsoop_grade_calculator-0.1.5.dist-info/METADATA
catsoop_grade_calculator-0.1.5.dist-info/WHEEL
catsoop_grade_calculator-0.1.5.dist-info/RECORD
