Metadata-Version: 2.1
Name: catsoop_grade_calculator
Version: 0.1.5
Summary: A set of scripts to calculate a cumulative grade for classes on CAT-SOOP.
Author: ricE06
Author-email: ezzhaneri06@gmail.com
Requires-Python: >=3.10,<4.0
Classifier: Programming Language :: Python :: 3
Classifier: Programming Language :: Python :: 3.10
Classifier: Programming Language :: Python :: 3.11
Classifier: Programming Language :: Python :: 3.12
Requires-Dist: bs4 (>=0.0.2,<0.0.3)
Requires-Dist: requests (>=2.32.3,<3.0.0)
